{
  "about": {
    "name": "Masaaki Morishita",
    "birthday": "1990/08/30",
    "school": {
      "name": "Wakayama Univ",
      "laboratory": "Software Design Lab"
    },
    "language": [
      "Ruby",
      "JavaScript",
      "PHP"
    ]
  },

  "links": [
    {
      "url": "http://blog.morishitter.com",
      "name": "No web, No life."
    },
    {
      "url": "http://morishitter.hatenablog.com",
      "name": "Hatena Blog"
    },
    {
      "url": "http://b.hatena.ne.jp/morishitter",
      "name": "Hatena Bookmark"
    },
    {
      "url": "https://github.com/morishitter",
      "name": "GitHub",
      "account_name": "morishitter"
    },
    {
      "url": "http://twitter.com/_morishitter",
      "name": "Twitter",
      "account_name": "_morishitter"
    }
  ]
}
